datapipes/__init__.py
datapipes/datapipe.py
datapipes/datapipe_types.py
datapipes/initialize_datapipe.py
datapipes/memory.py
datapipes/types.py
interface/__init__.py
interface/base.py
llms/__init__.py
llms/anthropic.py
llms/initialize_llm.py
llms/llm.py
llms/llm_types.py
llms/openai.py
llms/types.py
orchestrator/__init__.py
orchestrator/action.py
orchestrator/orchestrator.py
planners/__init__.py
planners/action.py
planners/initialize_planner.py
planners/planner.py
planners/planner_types.py
planners/tree_of_thought.py
planners/types.py
planners/react/__init__.py
planners/react/base.py
response_generators/__init__.py
response_generators/initialize_response_generator.py
response_generators/response_generator.py
response_generators/response_generator_types.py
response_generators/types.py
tasks/__init__.py
tasks/ask_user.py
tasks/google_translator.py
tasks/initialize_task.py
tasks/read_from_datapipe.py
tasks/run_python_code.py
tasks/serpapi.py
tasks/task.py
tasks/task_types.py
tasks/test_file.py
tasks/types.py
tasks/affect/AE.py
tasks/affect/Predictor.py
tasks/affect/__init__.py
tasks/affect/activity_analysis.py
tasks/affect/activity_get.py
tasks/affect/base.py
tasks/affect/ppg_analysis.py
tasks/affect/ppg_get.py
tasks/affect/sleep_analysis.py
tasks/affect/sleep_get.py
tasks/affect/stress_analysis.py
tasks/playwright/__init__.py
tasks/playwright/base.py
tasks/playwright/click.py
tasks/playwright/current_page.py
tasks/playwright/extract_hyperlinks.py
tasks/playwright/extract_text.py
tasks/playwright/get_elements.py
tasks/playwright/navigate.py
tasks/playwright/navigate_back.py
tasks/playwright/utils.py
CHAa-0.2.0.dist-info/LICENSE
CHAa-0.2.0.dist-info/METADATA
CHAa-0.2.0.dist-info/WHEEL
CHAa-0.2.0.dist-info/top_level.txt
CHAa-0.2.0.dist-info/RECORD
